CoreUtilities/__init__.py
CoreUtilities/_version.py
CoreUtilities/core_types.py
CoreUtilities/debugging.py
CoreUtilities/dictionaries.py
CoreUtilities/encrypt.py
CoreUtilities/enhanced_logging.py
CoreUtilities/functions.py
CoreUtilities/generics.py
CoreUtilities/git.py
CoreUtilities/iterables.py
CoreUtilities/lists.py
CoreUtilities/numerics.py
CoreUtilities/parrallelization.py
CoreUtilities/search.py
CoreUtilities/serialization.py
CoreUtilities/signature.py
CoreUtilities/strings.py
coreutilities-0.0.81.dist-info/METADATA
coreutilities-0.0.81.dist-info/WHEEL
coreutilities-0.0.81.dist-info/licenses/LICENSE
coreutilities-0.0.81.dist-info/RECORD
