Metadata-Version: 2.4
Name: CoreUtilities
Version: 0.0.81
Summary: A comprehensive collection of Python utility functions for data science, file operations, and general-purpose programming
Project-URL: Homepage, https://github.com/Ruppert20/CoreUtils-Python
Project-URL: Documentation, https://github.com/Ruppert20/CoreUtils-Python
Project-URL: Bug Tracker, https://github.com/Ruppert20/CoreUtils-Python/issues
Project-URL: Source Code, https://github.com/Ruppert20/CoreUtils-Python
Author: @Ruppert20
License: MIT
License-File: LICENSE
Keywords: data-science,encryption,helpers,numpy,pandas,serialization,testing,utilities
Classifier: Development Status :: 4 - Beta
Classifier: Intended Audience :: Developers
Classifier: Intended Audience :: Science/Research
Classifier: License :: OSI Approved :: MIT License
Classifier: Operating System :: OS Independent
Classifier: Programming Language :: Python :: 3
Classifier: Programming Language :: Python :: 3 :: Only
Classifier: Programming Language :: Python :: 3.12
Classifier: Programming Language :: Python :: 3.13
Classifier: Programming Language :: Python :: 3.14
Classifier: Topic :: Scientific/Engineering
Classifier: Topic :: Software Development :: Libraries :: Python Modules
Classifier: Topic :: Utilities
Requires-Python: >=3.12
Requires-Dist: cryptography>=45.0.7
Requires-Dist: numpy<3.0.0,>=2.3.0
Requires-Dist: pandas<3.0.0,>=2.3.0
Requires-Dist: pyyaml>=6.0.2
Requires-Dist: tqdm<5.0.0,>=4.67.0
Provides-Extra: dev
Requires-Dist: black>=24.0.0; extra == 'dev'
Requires-Dist: flake8>=7.0.0; extra == 'dev'
Requires-Dist: mypy>=1.8.0; extra == 'dev'
Requires-Dist: pytest-cov>=4.1.0; extra == 'dev'
Requires-Dist: pytest<8.0.0,>=7.4.0; extra == 'dev'
Provides-Extra: optional
Requires-Dist: polars<2.0.0,>=1.33.0; extra == 'optional'
Requires-Dist: pyarrow<25.0.0,>=21.0.0; extra == 'optional'
